IC_design/VerilogHDL/4bit_Counter/CDC_HandShake.v
module CDC_HandShake(
	input wire clk, 
	input wire reset_b,
	input wire a_gray_data,
	input a_clk_en,
	output reg b_done = 1
);

reg [8:0] b_gray_cnt = 0;

always @ (posedge clk or negedge reset_b) begin
	if(!a_clk_en) begin
		b_done <= 0;
		b_gray_cnt <= { b_gray_cnt[7:0], a_gray_data };
		if(b_gray_cnt[8] == 1) begin
			b_gray_cnt = 0;
			b_done <= 1;
		end
	end
end
endmodule

IC_design/VerilogHDL/4bit_Counter/Counter_4bit.v
module Counter_4bit #(parameter integer cnt = 0)
(
	input wire clk,
	input wire reset_b,
	input wire b_done,
	input wire en_handshake,
	output reg [8:0] a_gray_cnt = 0,
	output reg a_gray_data = 0,
	output reg a_clk_en = 1
);

reg [8:0] tmp_gray_cnt = 0;

always @ ( posedge clk or negedge reset_b ) begin

	//a_clk_en = en_shake;
	if(!reset_b) begin
		a_clk_en <= 1;
		a_gray_cnt <= 0;
	end
	else if(!a_clk_en) begin
		if( en_handshake == 1 ) begin
			a_clk_en = 0;
		end
		if(b_done) begin
			a_clk_en <= 1;
			a_gray_cnt <= 0;
		end
		//a_gray_data <= 1'b1;
		a_gray_data <= a_gray_cnt[8];
		a_gray_cnt <= { a_gray_cnt[7:0] , 1'b0 };
	end
	else begin
		if( en_handshake == 1 ) begin
			a_clk_en = 0;
		end
		a_gray_cnt <= (a_gray_cnt + cnt > 5'b01111) ? 4'b1111 : a_gray_cnt + cnt;
		if(!a_clk_en) begin
			tmp_gray_cnt = a_gray_cnt;
			a_gray_cnt[7] = tmp_gray_cnt[7];
			a_gray_cnt[6] = tmp_gray_cnt[7] ^ tmp_gray_cnt[6];
			a_gray_cnt[5] = tmp_gray_cnt[7] ^ tmp_gray_cnt[6] ^ tmp_gray_cnt[5] ;
			a_gray_cnt[4] = tmp_gray_cnt[7] ^ tmp_gray_cnt[6] ^ tmp_gray_cnt[5] ^ tmp_gray_cnt[4];
			a_gray_cnt[3] = tmp_gray_cnt[7] ^ tmp_gray_cnt[6] ^ tmp_gray_cnt[5] ^ tmp_gray_cnt[4] ^ tmp_gray_cnt[3];
			a_gray_cnt[2] = tmp_gray_cnt[7] ^ tmp_gray_cnt[6] ^ tmp_gray_cnt[5] ^ tmp_gray_cnt[4] ^ tmp_gray_cnt[3] ^ tmp_gray_cnt[2];
			a_gray_cnt[1] = tmp_gray_cnt[7] ^ tmp_gray_cnt[6] ^ tmp_gray_cnt[5] ^ tmp_gray_cnt[4] ^ tmp_gray_cnt[3] ^ tmp_gray_cnt[2] ^ tmp_gray_cnt[1];
			a_gray_cnt[0] = tmp_gray_cnt[7] ^ tmp_gray_cnt[6] ^ tmp_gray_cnt[5] ^ tmp_gray_cnt[4] ^ tmp_gray_cnt[3] ^ tmp_gray_cnt[2] ^ tmp_gray_cnt[1] ^ tmp_gray_cnt[0];
			a_gray_cnt[8] = 1;
		end
	end
end
endmodule

IC_design/VerilogHDL/4bit_Counter/tb_Counter_HandShake.v
`timescale 1ns/ 1ps
module tb_Counter_HandShake;
parameter integer cnt = 3;
reg A_CLK, B_CLK, RSTB, HandShake; 
wire A_CNT_EN, B_DONE;
wire A_GRAY_DATA;
wire [8:0] A_GRAY_DATA_TMP;
Counter_4bit #(.cnt(cnt)) u0(.clk(A_CLK), .reset_b(RSTB), .b_done(B_DONE), .en_handshake(HandShake), .a_gray_cnt(A_GRAY_DATA_TMP) , .a_gray_data(A_GRAY_DATA), .a_clk_en(A_CNT_EN));
CDC_HandShake u1(.clk(B_CLK), .reset_b(RSTB), .a_gray_data(A_GRAY_DATA), .a_clk_en(A_CNT_EN), .b_done(B_DONE));
	initial begin
		A_CLK = 1;
		B_CLK = 1;
		RSTB = 1;
		HandShake = 0;
		forever A_CLK = #5 ~A_CLK;
	end
	initial begin
		forever B_CLK = #6 ~B_CLK;
	end
	initial begin
		RSTB = ~RSTB;
		#5;
		RSTB = ~RSTB;
		#20;
		HandShake = ~HandShake;
		#20;
		HandShake = ~HandShake;
		#300;
		RSTB = ~RSTB;
		#50;
		RSTB = ~RSTB;
		HandShake = ~HandShake;
		#20;
		HandShake = ~HandShake;
		#300;
		$display("Hello, Counter_HandShake!");
		$finish;
	end
	initial begin
		$dumpfile("waveform.vcd");
		$dumpvars(0, tb_Counter_HandShake);
	end
endmodule

IC_design/VerilogHDL/4bit_Counter/waveform.vcd
$date
	Wed Apr 12 16:57:54 2023
$end
$version
	Icarus Verilog
$end
$timescale
	1ps
$end
$scope module tb_Counter_HandShake $end
$var wire 1 ! B_DONE $end
$var wire 9 " A_GRAY_DATA_TMP [8:0] $end
$var wire 1 # A_GRAY_DATA $end
$var wire 1 $ A_CNT_EN $end
$var parameter 32 % cnt $end
$var reg 1 & A_CLK $end
$var reg 1 ' B_CLK $end
$var reg 1 ( HandShake $end
$var reg 1 ) RSTB $end
$scope module u0 $end
$var wire 1 & clk $end
$var wire 1 ( en_handshake $end
$var wire 1 ) reset_b $end
$var wire 1 ! b_done $end
$var parameter 32 * cnt $end
$var reg 1 $ a_clk_en $end
$var reg 9 + a_gray_cnt [8:0] $end
$var reg 1 # a_gray_data $end
$var reg 9 , tmp_gray_cnt [8:0] $end
$upscope $end
$scope module u1 $end
$var wire 1 $ a_clk_en $end
$var wire 1 # a_gray_data $end
$var wire 1 ' clk $end
$var wire 1 ) reset_b $end
$var reg 1 ! b_done $end
$var reg 9 - b_gray_cnt [8:0] $end
$upscope $end
$upscope $end
$enddefinitions $end
$comment Show the parameter values. $end
$dumpall
b11 *
b11 %
$end
#0
$dumpvars
b0 -
b0 ,
b0 +
0)
0(
1'
1&
1$
0#
b0 "
1!
$end
#5000
1)
0&
#6000
0'
#10000
b11 "
b11 +
1&
#12000
1'
#15000
0&
#18000
0'
#20000
b110 "
b110 +
1&
#24000
1'
#25000
0&
1(
#30000
b1001 "
b1001 +
b110 ,
0$
1&
0'
#35000
0&
#36000
0!
1'
#40000
b10010 "
b10010 +
1&
#42000
0'
#45000
0&
0(
#48000
1'
#50000
b100100 "
b100100 +
1&
#54000
0'
#55000
0&
#60000
b1001000 "
b1001000 +
1&
1'
#65000
0&
#66000
0'
#70000
b10010000 "
b10010000 +
1&
#72000
1'
#75000
0&
#78000
0'
#80000
b100100000 "
b100100000 +
1&
#84000
1'
#85000
0&
#90000
b1000000 "
b1000000 +
1#
1&
0'
#95000
0&
#96000
b1 -
1'
#100000
b10000000 "
b10000000 +
0#
1&
#102000
0'
#105000
0&
#108000
b10 -
1'
#110000
b100000000 "
b100000000 +
1&
#114000
0'
#115000
0&
#120000
b0 "
b0 +
1#
b100 -
1&
1'
#125000
0&
#126000
0'
#130000
0#
1&
#132000
b1000 -
1'
#135000
0&
#138000
0'
#140000
1&
#144000
b10000 -
1'
#145000
0&
#150000
1&
0'
#155000
0&
#156000
b100000 -
1'
#160000
1&
#162000
0'
#165000
0&
#168000
b1000000 -
1'
#170000
1&
#174000
0'
#175000
0&
#180000
b10000000 -
1&
1'
#185000
0&
#186000
0'
#190000
1&
#192000
b100000000 -
1'
#195000
0&
#198000
0'
#200000
1&
#204000
1!
b0 -
1'
#205000
0&
#210000
1$
1&
0'
#215000
0&
#216000
1'
#220000
b11 "
b11 +
1&
#222000
0'
#225000
0&
#228000
1'
#230000
b110 "
b110 +
1&
#234000
0'
#235000
0&
#240000
b1001 "
b1001 +
1&
1'
#245000
0&
#246000
0'
#250000
b1100 "
b1100 +
1&
#252000
1'
#255000
0&
#258000
0'
#260000
b1111 "
b1111 +
1&
#264000
1'
#265000
0&
#270000
1&
0'
#275000
0&
#276000
1'
#280000
1&
#282000
0'
#285000
0&
#288000
1'
#290000
1&
#294000
0'
#295000
0&
#300000
1&
1'
#305000
0&
#306000
0'
#310000
1&
#312000
1'
#315000
0&
#318000
0'
#320000
1&
#324000
1'
#325000
0&
#330000
1&
0'
#335000
0&
#336000
1'
#340000
1&
#342000
0'
#345000
b0 "
b0 +
0&
0)
#348000
1'
#350000
1&
#354000
0'
#355000
0&
#360000
1&
1'
#365000
0&
#366000
0'
#370000
1&
#372000
1'
#375000
0&
#378000
0'
#380000
1&
#384000
1'
#385000
0&
#390000
1&
0'
#395000
0&
1(
1)
#396000
1'
#400000
b11 "
b11 +
b0 ,
0$
1&
#402000
0'
#405000
0&
#408000
0!
1'
#410000
b110 "
b110 +
1&
#414000
0'
#415000
0&
0(
#420000
b1100 "
b1100 +
1&
1'
#425000
0&
#426000
0'
#430000
b11000 "
b11000 +
1&
#432000
1'
#435000
0&
#438000
0'
#440000
b110000 "
b110000 +
1&
#444000
1'
#445000
0&
#450000
b1100000 "
b1100000 +
1&
0'
#455000
0&
#456000
1'
#460000
b11000000 "
b11000000 +
1&
#462000
0'
#465000
0&
#468000
1'
#470000
b110000000 "
b110000000 +
1&
#474000
0'
#475000
0&
#480000
b100000000 "
b100000000 +
1#
1&
1'
#485000
0&
#486000
0'
#490000
b0 "
b0 +
1&
#492000
b1 -
1'
#495000
0&
#498000
0'
#500000
0#
1&
#504000
b10 -
1'
#505000
0&
#510000
1&
0'
#515000
0&
#516000
b100 -
1'
#520000
1&
#522000
0'
#525000
0&
#528000
b1000 -
1'
#530000
1&
#534000
0'
#535000
0&
#540000
b10000 -
1&
1'
#545000
0&
#546000
0'
#550000
1&
#552000
b100000 -
1'
#555000
0&
#558000
0'
#560000
1&
#564000
b1000000 -
1'
#565000
0&
#570000
1&
0'
#575000
0&
#576000
b10000000 -
1'
#580000
1&
#582000
0'
#585000
0&
#588000
b100000000 -
1'
#590000
1&
#594000
0'
#595000
0&
#600000
1!
b0 -
1&
1'
#605000
0&
#606000
0'
#610000
1$
1&
#612000
1'
#615000
0&
#618000
0'
#620000
b11 "
b11 +
1&
#624000
1'
#625000
0&
#630000
b110 "
b110 +
1&
0'
#635000
0&
#636000
1'
#640000
b1001 "
b1001 +
1&
#642000
0'
#645000
0&
#648000
1'
#650000
b1100 "
b1100 +
1&
#654000
0'
#655000
0&
#660000
b1111 "
b1111 +
1&
1'
